screen_tracker/__init__.py
screen_tracker/report.py
screen_tracker/tracker.py
screen_tracker-0.1.0.dist-info/METADATA
screen_tracker-0.1.0.dist-info/WHEEL
screen_tracker-0.1.0.dist-info/top_level.txt
screen_tracker-0.1.0.dist-info/RECORD
